{"sections":{"main":{"type":"main-page","settings":{"show_title":false,"show_breadcrumb":false,"page_width":"medium"}},"8a8b8d04-1acf-49cc-8ca5-f64937e76bd6":{"type":"hero-image","disabled":true,"settings":{"image":"shopify:\/\/shop_images\/MARKETING-MATERIAL-TOPBANNER_2400x_3d8b829d-36ee-4434-b6c2-d7fb24839be8.jpg","image_mob":"shopify:\/\/shop_images\/MARKETING-MATERIAL-TOPBANNER_2400x_3d8b829d-36ee-4434-b6c2-d7fb24839be8.jpg"}},"ce78002f-cc72-4d1c-b3c4-1c90ef5f4502":{"type":"multi-column","blocks":{"template--15210794352701__ce78002f-cc72-4d1c-b3c4-1c90ef5f4502-168594903618033c4e-0":{"type":"item","disabled":true,"settings":{"image":"shopify:\/\/shop_images\/DS18-LOGO-GUIDELINES.jpg","image_width":100,"image_border":"rgba(0,0,0,0)","title":"DS18 Logo Guidelines PDF","content":"","link_text":"","link_url":"https:\/\/cdn.shopify.com\/s\/files\/1\/0018\/0142\/0861\/files\/LOGO_DS18_RED_GUIDELINES.pdf?v=1645043366","enable_open_link":true,"link_style":"link","text_alignment":"left","vertical_alignment":"start"}},"03262a95-634a-4a3b-8376-2fad943e8b43":{"type":"item","disabled":true,"settings":{"image":"shopify:\/\/shop_images\/DS18-WLIL-LOGO-GUIDELINES.jpg","image_width":100,"image_border":"rgba(0,0,0,0)","title":"DS18 We Like It Loud Logo Guidelines PDF","content":"","link_text":"","link_url":"https:\/\/cdn.shopify.com\/s\/files\/1\/0018\/0142\/0861\/files\/LOGO_DS18_WELIKEITLOUD_GUIDELINES.pdf","enable_open_link":true,"link_style":"link","text_alignment":"left","vertical_alignment":"start"}},"a6cc6faf-8883-46da-9e31-6c4d4903980d":{"type":"item","settings":{"image":"shopify:\/\/shop_images\/DS18-LINE-LOGO-GUIDELINES.jpg","image_width":100,"image_border":"rgba(0,0,0,0)","title":"DS18 Logo Guidelines PDF","content":"","link_text":"","link_url":"https:\/\/cdn.shopify.com\/s\/files\/1\/0018\/0142\/0861\/files\/DS18_LINE_LOGO_GUIDELINES.pdf?v=1706215861","enable_open_link":true,"link_style":"link","text_alignment":"left","vertical_alignment":"start"}}},"block_order":["template--15210794352701__ce78002f-cc72-4d1c-b3c4-1c90ef5f4502-168594903618033c4e-0","03262a95-634a-4a3b-8376-2fad943e8b43","a6cc6faf-8883-46da-9e31-6c4d4903980d"],"disabled":true,"custom_css":[".multi-column {border-bottom: 1px solid #000; padding-bottom: 50px;}"],"settings":{"reveal_on_scroll":true,"stack_items":true,"subheading":"","title":"LOGOS","content":"","column_alignment":"left","mobile_item_size":"large","desktop_item_size":"large","spacing":"tight","background":"rgba(0,0,0,0)","text_color":"rgba(0,0,0,0)"}},"4c7ca175-8b57-4b28-9f98-77b5bec478f7":{"type":"multi-column","blocks":{"4462d1ed-d7a8-4ec5-ade5-0ce1bdbb5a37":{"type":"item","disabled":true,"settings":{"image":"shopify:\/\/shop_images\/DS18-RED-LOGO.jpg","image_width":100,"image_border":"rgba(0,0,0,0)","title":"DS18 RED Logo","content":"","link_text":"","link_url":"https:\/\/cdn.shopify.com\/s\/files\/1\/0018\/0142\/0861\/files\/LOGO_DS18_RED.pdf","enable_open_link":true,"link_style":"link","text_alignment":"left","vertical_alignment":"start"}},"246a1f0f-c47f-4e72-9691-32036a532045":{"type":"item","settings":{"image":"shopify:\/\/shop_images\/DS18-BLACK-LOGO.jpg","image_width":100,"image_border":"rgba(0,0,0,0)","title":"DS18 Black Logo","content":"","link_text":"","link_url":"https:\/\/cdn.shopify.com\/s\/files\/1\/0018\/0142\/0861\/files\/DS18_LOGO.pdf?v=1706216365","enable_open_link":true,"link_style":"link","text_alignment":"left","vertical_alignment":"start"}},"item_E7UNLx":{"type":"item","disabled":true,"settings":{"image":"shopify:\/\/shop_images\/LOGO-DS18-WLIL-BLACK.png","image_width":100,"image_border":"rgba(0,0,0,0)","title":"DS18 We Like It Loud BLACK Logo","content":"","link_text":"","link_url":"https:\/\/cdn.shopify.com\/s\/files\/1\/0018\/0142\/0861\/files\/LOGO_DS18_WLIL_BLACK.pdf?v=1706216716","enable_open_link":true,"link_style":"link","text_alignment":"left","vertical_alignment":"start"}},"718bd513-a830-4fb9-981c-19a27379b13e":{"type":"item","disabled":true,"settings":{"image":"shopify:\/\/shop_images\/DS18-WELIKEITLOUD-LOGO.jpg","image_width":100,"image_border":"rgba(0,0,0,0)","title":"DS18 We Like It Loud BLACK\/RED Logo","content":"","link_text":"","link_url":"https:\/\/cdn.shopify.com\/s\/files\/1\/0018\/0142\/0861\/files\/DS18_WLIL_BLACK_RED_LOGO.pdf","enable_open_link":true,"link_style":"link","text_alignment":"left","vertical_alignment":"start"}}},"block_order":["4462d1ed-d7a8-4ec5-ade5-0ce1bdbb5a37","246a1f0f-c47f-4e72-9691-32036a532045","item_E7UNLx","718bd513-a830-4fb9-981c-19a27379b13e"],"disabled":true,"custom_css":[".multi-column {border-bottom: 1px solid #000; padding-bottom: 50px;}"],"settings":{"reveal_on_scroll":true,"stack_items":true,"subheading":"","title":"","content":"","column_alignment":"left","mobile_item_size":"large","desktop_item_size":"large","spacing":"tight","background":"rgba(0,0,0,0)","text_color":"rgba(0,0,0,0)"}},"multi_column_fq3X9i":{"type":"multi-column","blocks":{"item_DMdDq8":{"type":"item","disabled":true,"settings":{"image":"shopify:\/\/shop_images\/DS18-RED-LOGO.jpg","image_width":100,"image_border":"rgba(0,0,0,0)","title":"DS18 RED Logo","content":"","link_text":"","link_url":"https:\/\/cdn.shopify.com\/s\/files\/1\/0018\/0142\/0861\/files\/LOGO_DS18_RED.pdf","enable_open_link":true,"link_style":"link","text_alignment":"left","vertical_alignment":"start"}},"item_faXDJW":{"type":"item","disabled":true,"settings":{"image":"shopify:\/\/shop_images\/DS18-BLACK-LOGO.jpg","image_width":100,"image_border":"rgba(0,0,0,0)","title":"DS18 Black Logo","content":"","link_text":"","link_url":"https:\/\/cdn.shopify.com\/s\/files\/1\/0018\/0142\/0861\/files\/DS18_LOGO.pdf?v=1706216365","enable_open_link":true,"link_style":"link","text_alignment":"left","vertical_alignment":"start"}},"item_bB99Xz":{"type":"item","disabled":true,"settings":{"image":"shopify:\/\/shop_images\/DS18-WELIKEITLOUD-LOGO.jpg","image_width":100,"image_border":"rgba(0,0,0,0)","title":"DS18 We Like It Loud BLACK\/RED Logo","content":"","link_text":"","link_url":"https:\/\/cdn.shopify.com\/s\/files\/1\/0018\/0142\/0861\/files\/DS18_WLIL_BLACK_RED_LOGO.pdf","enable_open_link":true,"link_style":"link","text_alignment":"left","vertical_alignment":"start"}},"item_NLacW7":{"type":"item","settings":{"image":"shopify:\/\/shop_images\/LOGO-DS18-WLIL-BLACK.png","image_width":100,"image_border":"rgba(0,0,0,0)","title":"DS18 We Like It Loud BLACK Logo","content":"","link_text":"","link_url":"https:\/\/cdn.shopify.com\/s\/files\/1\/0018\/0142\/0861\/files\/LOGO_DS18_WLIL_BLACK.pdf?v=1706216716","enable_open_link":true,"link_style":"link","text_alignment":"left","vertical_alignment":"start"}},"item_c7cbVa":{"type":"item","settings":{"image":"shopify:\/\/shop_images\/WE-LIKE-IT-LOUD-SIMPLE.png","image_width":100,"image_border":"rgba(0,0,0,0)","title":"WE LIKE IT LOUD SIMPLE","content":"","link_text":"","link_url":"https:\/\/cdn.shopify.com\/s\/files\/1\/0018\/0142\/0861\/files\/WE_LIKE_IT_LOUD_SIMPLE.pdf?v=1706216963","enable_open_link":true,"link_style":"link","text_alignment":"left","vertical_alignment":"start"}}},"block_order":["item_DMdDq8","item_faXDJW","item_bB99Xz","item_NLacW7","item_c7cbVa"],"disabled":true,"custom_css":[".multi-column {border-bottom: 1px solid #000; padding-bottom: 50px;}"],"settings":{"reveal_on_scroll":true,"stack_items":true,"subheading":"","title":"","content":"","column_alignment":"left","mobile_item_size":"large","desktop_item_size":"large","spacing":"tight","background":"rgba(0,0,0,0)","text_color":"rgba(0,0,0,0)"}},"2b6a7769-c8a2-4d5b-8bd4-05e7c24f83c8":{"type":"multi-column","blocks":{"2f5fecc7-b1e1-495e-aff0-bdb5a9f8cc38":{"type":"item","settings":{"image":"shopify:\/\/shop_images\/DS18-LONG-LINE-LOGO.jpg","image_width":100,"image_border":"rgba(0,0,0,0)","title":"DS18 Long Line Logo","content":"","link_text":"","link_url":"https:\/\/cdn.shopify.com\/s\/files\/1\/0018\/0142\/0861\/files\/DS18_LINE_LOGO.pdf?v=1706216308","enable_open_link":true,"link_style":"link","text_alignment":"left","vertical_alignment":"start"}},"6929c8ed-8a13-44c2-bfe5-94202faf80fe":{"type":"item","disabled":true,"settings":{"image":"shopify:\/\/shop_images\/DS18-SHORT-LINE-LOGO.jpg","image_width":100,"image_border":"rgba(0,0,0,0)","title":"DS18 Short Line Logo","content":"","link_text":"","link_url":"https:\/\/cdn.shopify.com\/s\/files\/1\/0018\/0142\/0861\/files\/LOGO_DS18_SHORT_LINE.pdf","enable_open_link":true,"link_style":"link","text_alignment":"left","vertical_alignment":"start"}}},"block_order":["2f5fecc7-b1e1-495e-aff0-bdb5a9f8cc38","6929c8ed-8a13-44c2-bfe5-94202faf80fe"],"disabled":true,"custom_css":[],"settings":{"reveal_on_scroll":true,"stack_items":true,"subheading":"","title":"","content":"","column_alignment":"left","mobile_item_size":"large","desktop_item_size":"large","spacing":"loose","background":"rgba(0,0,0,0)","text_color":"rgba(0,0,0,0)"}},"8f93df71-0e31-4153-8c1b-87861192fb37":{"type":"multi-column","blocks":{"6f351321-b25c-4318-9c01-ddffeefbaadb":{"type":"item","settings":{"image":"shopify:\/\/shop_images\/DS18-WOLF-FACE-LOGO.jpg","image_width":100,"image_border":"rgba(0,0,0,0)","title":"DS18 Wolf Face Logo","content":"","link_text":"","link_url":"https:\/\/cdn.shopify.com\/s\/files\/1\/0018\/0142\/0861\/files\/LOGO_DS18_LONG_LINE.pdf","enable_open_link":true,"link_style":"link","text_alignment":"left","vertical_alignment":"start"}},"b2dd9b76-295a-449c-9b47-bad8520ed06d":{"type":"item","settings":{"image":"shopify:\/\/shop_images\/DS18-WOLF-FACE-WLIL-LOGO.jpg","image_width":100,"image_border":"rgba(0,0,0,0)","title":"DS18 Wolf Face We Like It Loud Logo","content":"","link_text":"","link_url":"https:\/\/cdn.shopify.com\/s\/files\/1\/0018\/0142\/0861\/files\/WOLF_PAINT_FACE_DS18_WLIL.pdf","enable_open_link":true,"link_style":"link","text_alignment":"left","vertical_alignment":"start"}},"d0d876e7-ced6-45a7-a506-9b149267e80d":{"type":"item","settings":{"image":"shopify:\/\/shop_images\/DS18-WOLF-MASK-LOGO.jpg","image_width":100,"image_border":"rgba(0,0,0,0)","title":"DS18 Wolf Mask Logo","content":"","link_text":"","link_url":"https:\/\/cdn.shopify.com\/s\/files\/1\/0018\/0142\/0861\/files\/WOLF_PAINT_FACE_DS18_MASK.pdf","enable_open_link":true,"link_style":"link","text_alignment":"left","vertical_alignment":"start"}}},"block_order":["6f351321-b25c-4318-9c01-ddffeefbaadb","b2dd9b76-295a-449c-9b47-bad8520ed06d","d0d876e7-ced6-45a7-a506-9b149267e80d"],"disabled":true,"custom_css":[],"settings":{"reveal_on_scroll":true,"stack_items":true,"subheading":"","title":"","content":"","column_alignment":"left","mobile_item_size":"large","desktop_item_size":"large","spacing":"tight","background":"rgba(0,0,0,0)","text_color":"rgba(0,0,0,0)"}},"multi_column_gGmBkK":{"type":"multi-column","blocks":{"item_fYQBx3":{"type":"item","settings":{"image":"shopify:\/\/shop_images\/DS18-LINE-LOGO-GUIDELINES.jpg","image_width":100,"image_border":"rgba(0,0,0,0)","title":"DS18 Logo Guidelines PDF","content":"","link_text":"","link_url":"https:\/\/cdn.shopify.com\/s\/files\/1\/0018\/0142\/0861\/files\/DS18_LINE_LOGO_GUIDELINES.pdf?v=1706215861","enable_open_link":true,"link_style":"link","text_alignment":"left","vertical_alignment":"start"}},"item_4HWRC4":{"type":"item","settings":{"image":"shopify:\/\/shop_images\/DS18-BLACK-LOGO.jpg","image_width":100,"image_border":"rgba(0,0,0,0)","title":"DS18 Black Logo","content":"","link_text":"","link_url":"https:\/\/cdn.shopify.com\/s\/files\/1\/0018\/0142\/0861\/files\/DS18_LOGO.pdf?v=1706216365","enable_open_link":true,"link_style":"link","text_alignment":"left","vertical_alignment":"start"}},"item_fyiaE3":{"type":"item","settings":{"image":"shopify:\/\/shop_images\/LOGO-DS18-WLIL-BLACK.png","image_width":100,"image_border":"rgba(0,0,0,0)","title":"DS18 We Like It Loud BLACK Logo","content":"","link_text":"","link_url":"https:\/\/cdn.shopify.com\/s\/files\/1\/0018\/0142\/0861\/files\/LOGO_DS18_WLIL_BLACK.pdf?v=1706216716","enable_open_link":true,"link_style":"link","text_alignment":"left","vertical_alignment":"start"}},"item_kGqKqe":{"type":"item","settings":{"image":"shopify:\/\/shop_images\/WE-LIKE-IT-LOUD-SIMPLE.png","image_width":100,"image_border":"rgba(0,0,0,0)","title":"WE LIKE IT LOUD SIMPLE","content":"","link_text":"","link_url":"https:\/\/cdn.shopify.com\/s\/files\/1\/0018\/0142\/0861\/files\/WE_LIKE_IT_LOUD_SIMPLE.pdf?v=1706216963","enable_open_link":true,"link_style":"link","text_alignment":"left","vertical_alignment":"start"}},"item_iVhgMK":{"type":"item","settings":{"image":"shopify:\/\/shop_images\/V2-DS18-LONG-LINE-LOGO.png","image_width":100,"image_border":"rgba(0,0,0,0)","title":"DS18 Long Line Logo","content":"","link_text":"","link_url":"https:\/\/cdn.shopify.com\/s\/files\/1\/0018\/0142\/0861\/files\/DS18_LINE_LOGO.pdf?v=1706216308","enable_open_link":true,"link_style":"link","text_alignment":"left","vertical_alignment":"start"}}},"block_order":["item_fYQBx3","item_4HWRC4","item_fyiaE3","item_kGqKqe","item_iVhgMK"],"settings":{"reveal_on_scroll":true,"stack_items":true,"subheading":"","title":"LOGOS","content":"","column_alignment":"left","mobile_item_size":"large","desktop_item_size":"large","spacing":"tight","background":"rgba(0,0,0,0)","text_color":"rgba(0,0,0,0)"}}},"order":["main","8a8b8d04-1acf-49cc-8ca5-f64937e76bd6","ce78002f-cc72-4d1c-b3c4-1c90ef5f4502","4c7ca175-8b57-4b28-9f98-77b5bec478f7","multi_column_fq3X9i","2b6a7769-c8a2-4d5b-8bd4-05e7c24f83c8","8f93df71-0e31-4153-8c1b-87861192fb37","multi_column_gGmBkK"]}